ipapy/__init__.py
ipapy/__main__.py
ipapy/arpabetmapper.py
ipapy/compatibility.py
ipapy/ipachar.py
ipapy/ipadescriptor.py
ipapy/ipastring.py
ipapy/kirshenbaummapper.py
ipapy/mapper.py
ipapy/data/__init__.py
ipapy/data/arpabet.dat
ipapy/data/ipa.dat
ipapy/data/kirshenbaum.dat
ipapy-0.0.9.0.data/scripts/ipapy
ipapy-0.0.9.0.dist-info/LICENSE
ipapy-0.0.9.0.dist-info/METADATA
ipapy-0.0.9.0.dist-info/WHEEL
ipapy-0.0.9.0.dist-info/top_level.txt
ipapy-0.0.9.0.dist-info/RECORD
